stackit/core/__init__.py
stackit/core/auth_methods/key_auth.py
stackit/core/auth_methods/token_auth.py
stackit/core/authorization.py
stackit/core/configuration.py
stackit_core-0.1.0.dist-info/LICENSE
stackit_core-0.1.0.dist-info/METADATA
stackit_core-0.1.0.dist-info/WHEEL
stackit_core-0.1.0.dist-info/RECORD
